scProjection/__init__.py
scProjection/architectures.py
scProjection/batchBackend.py
scProjection/deconvBackend.py
scProjection/deconvModel.py
scProjection/saving_utils.py
scProjection/utils.py
scProjection/vaeBackend.py
scProjection/vaeTrain.py
scProjection-0.22.dist-info/METADATA
scProjection-0.22.dist-info/WHEEL
scProjection-0.22.dist-info/top_level.txt
scProjection-0.22.dist-info/RECORD
