Metadata-Version: 2.1
Name: scProjection
Version: 0.22
Summary: Projection and Deconvolution using deep heirarchical and generative neural network.
Home-page: https://github.com/ucdavis/quonlab/tree/master/development/deconvAllen
Author: Nelson Johansen, Gerald Quon
Author-email: njjohansen@ucdavis.edu, gquon@ucdavis.edu
License: MIT
Platform: UNKNOWN
Classifier: Programming Language :: Python :: 3
Classifier: License :: OSI Approved :: MIT License
Classifier: Operating System :: OS Independent
Requires-Python: >=3.6
Requires-Dist: tensorflow
Requires-Dist: tensorflow-probability
Requires-Dist: sklearn
Requires-Dist: numpy
